setup.py
paymill/__init__.py
paymill/core.py
paymill.egg-info/PKG-INFO
paymill.egg-info/SOURCES.txt
paymill.egg-info/dependency_links.txt
paymill.egg-info/not-zip-safe
paymill.egg-info/top_level.txt