Metadata-Version: 1.0
Name: paymill
Version: 0.1.1
Summary: Minimal python API client library for Paymill API v2
Home-page: https://github.com/rutherford/Paymill
Author: Matt Rutherford
Author-email: rutherford@clientsideweb.net
License: MIT
Platform: UNKNOWN
